viriback2misp/__init__.py
viriback2misp/main.py
viriback2misp/lib/misp.py
viriback2misp/lib/viriback.py
viriback2misp/lib/__pycache__/misp.cpython-312.pyc
viriback2misp/lib/__pycache__/viriback.cpython-312.pyc
viriback2misp-0.3.dist-info/METADATA
viriback2misp-0.3.dist-info/WHEEL
viriback2misp-0.3.dist-info/entry_points.txt
viriback2misp-0.3.dist-info/top_level.txt
viriback2misp-0.3.dist-info/RECORD
