Metadata-Version: 2.1
Name: viriback2misp
Version: 0.3
Summary: Upload Viriback C2 Track data to MISP events
Home-page: https://github.com/santiag02/viriback2misp
Author: Camila Santiago
Keywords: C2,command and control,C2 Tracker,command & control,feed c2,infostealer,bot,malware
Requires-Dist: pandas
Requires-Dist: requests
Requires-Dist: pymisp
Requires-Dist: python-dateutil
